[
  {
    "redir": "/TeacherResources/ExploreLessons/56ec91d9-4479-4cb7-b297-a222b1b575f3",
    "catTitle": "Simple",
    "title": "Estampado de letras",
    "subtitle": "Conjunto de máquinas simples y motorizadas",
    "description": "Aplicar conocimientos y habilidades relacionados con palancas, levas, engranajes, observar y mejorar, y pruebas justas.",
    "categories": "VAPOR, Ingeniería, Tecnología",
    "duration": "45-90 min.",
    "level": "Avanzado",
    "grade": "Primaria Alta 9 - 11",
    "urlImg": "/img/lessonsImg/StampingLetters.webp",
    "id": "56ec91d9-4479-4cb7-b297-a222b1b575f3"
  }
]